temporal_scheduler/__init__.py
temporal_scheduler/temporal_scheduler.py
temporal_scheduler-2022.4.18.2.dist-info/LICENSE
temporal_scheduler-2022.4.18.2.dist-info/METADATA
temporal_scheduler-2022.4.18.2.dist-info/WHEEL
temporal_scheduler-2022.4.18.2.dist-info/top_level.txt
temporal_scheduler-2022.4.18.2.dist-info/RECORD
