Metadata-Version: 2.1
Name: temporal-scheduler
Version: 2022.4.18.2
Summary: Lightweight temporal scheduler for thread  synchronization and code execution
Home-page: https://github.com/piranha32/temporal_scheduler
Author: Jacek Radzikowski
Author-email: jacek.radzikowski@gmail.com
License: GPLv3
Platform: UNKNOWN
Classifier: Development Status :: 4 - Beta
Classifier: License :: OSI Approved :: MIT License
Classifier: Programming Language :: Python :: 3
Classifier: Operating System :: OS Independent
Requires-Python: >=3
License-File: LICENSE
Requires-Dist: sortedcontainers
